{
  "id": 88,
  "title": "If at First You Don't Succeed, Try, Try Again",
  "description": "A hapless imugi is determined to attain the form of a full-fledged dragon and gain entry to the gates of heaven. For a long time, things don't go well. Then, it meets a girl. The B&amp;N Sci-Fi &amp; Fantasy Blog presents an original short story by Campbell Award-nominated author Zen Cho.",
  "imageUrl": "https://i.gr-assets.com/images/S/compressed.photo.goodreads.com/books/1565795394l/43064429._SX98_.jpg",
  "isbn10": null,
  "isbn13": null,
  "kindleAsin": null,
  "numPages": 30,
  "goodreadsId": "43064429",
  "authors": [
    {
      "id": 88,
      "name": "Zen Cho"
    }
  ]
}
